ggetrs-0.1.87.dist-info/METADATA
ggetrs-0.1.87.dist-info/WHEEL
ggetrs-0.1.87.dist-info/licenses/LICENSE
ggetrs/__init__.py
ggetrs/ggetrs.cpython-39-darwin.so
ggetrs-0.1.87.dist-info/RECORD
