Metadata-Version: 2.3
Name: ggetrs
Version: 0.1.87
License-File: LICENSE
Summary: Biological querying and analysis
Keywords: bioinformatics
Home-Page: https://noamteyssier.github.io/ggetrs/
Author-email: Noam Teyssier <noam.teyssier@ucsf.edu>
License: MIT
Requires-Python: >=3.8
Project-URL: Homepage, https://noamteyssier.github.io/ggetrs
Project-URL: Repository, https://github.com/noamteyssier/ggetrs
